Scipycon2018SklearnJiaocheng/README.md
Scipycon2018SklearnJiaocheng/__init__.py
Scipycon2018SklearnJiaocheng/__main__.py
Scipycon2018SklearnJiaocheng/file.epub
Scipycon2018SklearnJiaocheng/index.html
Scipycon2018SklearnJiaocheng/css/__init__.py
Scipycon2018SklearnJiaocheng/css/annotations.css
Scipycon2018SklearnJiaocheng/css/main.css
Scipycon2018SklearnJiaocheng/css/normalize.css
Scipycon2018SklearnJiaocheng/css/popup.css
Scipycon2018SklearnJiaocheng/font/__init__.py
Scipycon2018SklearnJiaocheng/font/fontello.eot
Scipycon2018SklearnJiaocheng/font/fontello.svg
Scipycon2018SklearnJiaocheng/font/fontello.ttf
Scipycon2018SklearnJiaocheng/font/fontello.woff
Scipycon2018SklearnJiaocheng/img/__init__.py
Scipycon2018SklearnJiaocheng/img/annotator-glyph-sprite.png
Scipycon2018SklearnJiaocheng/img/annotator-icon-sprite.png
Scipycon2018SklearnJiaocheng/img/apple-touch-icon.png
Scipycon2018SklearnJiaocheng/img/cancelfullscreen.png
Scipycon2018SklearnJiaocheng/img/close.png
Scipycon2018SklearnJiaocheng/img/fullscreen.png
Scipycon2018SklearnJiaocheng/img/loader.gif
Scipycon2018SklearnJiaocheng/img/menu-icon.png
Scipycon2018SklearnJiaocheng/img/save.png
Scipycon2018SklearnJiaocheng/img/saved.png
Scipycon2018SklearnJiaocheng/img/settings-s.png
Scipycon2018SklearnJiaocheng/img/settings.png
Scipycon2018SklearnJiaocheng/img/star.png
Scipycon2018SklearnJiaocheng/js/__init__.py
Scipycon2018SklearnJiaocheng/js/epub.js
Scipycon2018SklearnJiaocheng/js/epub.min.js
Scipycon2018SklearnJiaocheng/js/epub.min.map
Scipycon2018SklearnJiaocheng/js/hooks.min.js
Scipycon2018SklearnJiaocheng/js/hooks.min.map
Scipycon2018SklearnJiaocheng/js/reader.js
Scipycon2018SklearnJiaocheng/js/reader.js.map
Scipycon2018SklearnJiaocheng/js/reader.min.js
Scipycon2018SklearnJiaocheng/js/reader.min.map
Scipycon2018SklearnJiaocheng/js/hooks/__init__.py
Scipycon2018SklearnJiaocheng/js/hooks/extensions/__init__.py
Scipycon2018SklearnJiaocheng/js/hooks/extensions/highlight.js
scipycon_2018_sklearn_jiaocheng-2024.3.3.0.dist-info/METADATA
scipycon_2018_sklearn_jiaocheng-2024.3.3.0.dist-info/WHEEL
scipycon_2018_sklearn_jiaocheng-2024.3.3.0.dist-info/entry_points.txt
scipycon_2018_sklearn_jiaocheng-2024.3.3.0.dist-info/top_level.txt
scipycon_2018_sklearn_jiaocheng-2024.3.3.0.dist-info/RECORD
